pangea_authz_fastmcp/__init__.py
pangea_authz_fastmcp/py.typed
pangea_authz_fastmcp/cli/__init__.py
pangea_authz_fastmcp/cli/transports.py
pangea_authz_fastmcp-0.2.1.dist-info/METADATA
pangea_authz_fastmcp-0.2.1.dist-info/WHEEL
pangea_authz_fastmcp-0.2.1.dist-info/entry_points.txt
pangea_authz_fastmcp-0.2.1.dist-info/licenses/LICENSE
pangea_authz_fastmcp-0.2.1.dist-info/RECORD
