Metadata-Version: 2.4
Name: pangea-authz-fastmcp
Version: 0.2.1
Summary: Pangea AuthZ integration for FastMCP
Project-URL: Homepage, https://github.com/pangeacyber/pangea-authz-fastmcp
Project-URL: Documentation, https://github.com/pangeacyber/pangea-authz-fastmcp
Project-URL: Source, https://github.com/pangeacyber/pangea-authz-fastmcp
Project-URL: Changelog, https://github.com/pangeacyber/pangea-authz-fastmcp/releases
Author-email: Pangea <support@pangea.cloud>
License-Expression: MIT
License-File: LICENSE
Requires-Python: >=3.11
Requires-Dist: fastmcp>=2.11.3
Requires-Dist: mcp>=1.13.1
Requires-Dist: pangea-sdk>=6.5.0
Requires-Dist: pydantic>=2.11.7
Provides-Extra: cli
Requires-Dist: beaupy>=3.10.1; extra == 'cli'
Requires-Dist: cyclopts>=3.23.0; extra == 'cli'
Requires-Dist: google-api-python-client>=2.179.0; extra == 'cli'
Requires-Dist: google-auth-httplib2>=0.2.0; extra == 'cli'
Requires-Dist: google-auth-oauthlib>=1.2.2; extra == 'cli'
Requires-Dist: pyjson5>=1.6.9; extra == 'cli'
